fint_core/__init__.py
fint_core/auth.py
fint_core/multiuser.py
fint_core-0.0.1.dist-info/METADATA
fint_core-0.0.1.dist-info/WHEEL
fint_core-0.0.1.dist-info/RECORD
